bits_aviso_python_sdk/__init__.py
bits_aviso_python_sdk/helpers/README.md
bits_aviso_python_sdk/helpers/__init__.py
bits_aviso_python_sdk/helpers/aesthetics.py
bits_aviso_python_sdk/helpers/bigquery.py
bits_aviso_python_sdk/helpers/files.py
bits_aviso_python_sdk/services/README.md
bits_aviso_python_sdk/services/__init__.py
bits_aviso_python_sdk/services/eip/README.md
bits_aviso_python_sdk/services/eip/__init__.py
bits_aviso_python_sdk/services/eip/payloads.py
bits_aviso_python_sdk/services/eip/solidserver.py
bits_aviso_python_sdk/services/foreman/README.md
bits_aviso_python_sdk/services/foreman/__init__.py
bits_aviso_python_sdk/services/foreman/payloads.py
bits_aviso_python_sdk/services/google/README.md
bits_aviso_python_sdk/services/google/__init__.py
bits_aviso_python_sdk/services/google/bigquery.py
bits_aviso_python_sdk/services/google/pubsub.py
bits_aviso_python_sdk/services/google/secretmanager.py
bits_aviso_python_sdk/services/google/sheets.py
bits_aviso_python_sdk/services/google/storage.py
bits_aviso_python_sdk/services/isilon/README.md
bits_aviso_python_sdk/services/isilon/__init__.py
bits_aviso_python_sdk/services/puppet/README.md
bits_aviso_python_sdk/services/puppet/__init__.py
bits_aviso_python_sdk/services/sap/README.md
bits_aviso_python_sdk/services/sap/__init__.py
bits_aviso_python_sdk/services/sap/payloads.py
bits_aviso_python_sdk/services/sentinelone/README.md
bits_aviso_python_sdk/services/sentinelone/__init__.py
bits_aviso_python_sdk/services/slack/README.md
bits_aviso_python_sdk/services/slack/__init__.py
bits_aviso_python_sdk/services/slack/payloads.py
bits_aviso_python_sdk/tests/configs/foreman_config.yml
bits_aviso_python_sdk/tests/foreman.py
bits_aviso_python_sdk/tests/google/bigquery.py
bits_aviso_python_sdk/tests/google/pubsub.py
bits_aviso_python_sdk/tests/google/secretmanager.py
bits_aviso_python_sdk/tests/google/sheets.py
bits_aviso_python_sdk/tests/google/storage.py
bits_aviso_python_sdk/tests/helpers.py
bits_aviso_python_sdk-1.10.6.dist-info/METADATA
bits_aviso_python_sdk-1.10.6.dist-info/WHEEL
bits_aviso_python_sdk-1.10.6.dist-info/RECORD
