Metadata-Version: 2.3
Name: bits-aviso-python-sdk
Version: 1.10.6
Summary: Repository containing python wrappers to various services for bits-aviso.
License: MIT
Author: Miranda Nguyen
Author-email: mirandanguyen98@gmail.com
Requires-Python: >=3.11,<4.0
Classifier: License :: OSI Approved :: MIT License
Classifier: Programming Language :: Python :: 3
Classifier: Programming Language :: Python :: 3.11
Classifier: Programming Language :: Python :: 3.12
Classifier: Programming Language :: Python :: 3.13
Requires-Dist: apypie (>=0.6.2,<0.7.0)
Requires-Dist: dnspython (>=2.7,<3.0)
Requires-Dist: google-api-python-client (>=2.143.0,<3.0.0)
Requires-Dist: google-cloud-bigquery (>=3.27.0,<4.0.0)
Requires-Dist: google-cloud-pubsub (>=2.22.0,<3.0.0)
Requires-Dist: google-cloud-secret-manager (>=2.20.1,<3.0.0)
Requires-Dist: google-cloud-storage (>=2.18.0,<3.0.0)
Requires-Dist: pdoc3 (>=0.11.1,<0.12.0)
Requires-Dist: pre-commit (>=3.8.0,<4.0.0)
Requires-Dist: progressbar2 (>=4.5.0,<5.0.0)
Requires-Dist: pypuppetdb (>=3.2.0,<4.0.0)
Requires-Dist: xmltodict (>=0.13.0,<0.14.0)
